smbl/__init__.py
smbl/include_all.snake
smbl/fasta/fasta.snake
smbl/fasta/fastafile.py
smbl/fasta/__init__.py
smbl/prog/prog.snake
smbl/prog/__init__.py
smbl/prog/plugins/bowtie.py
smbl/prog/plugins/seqan.py
smbl/prog/plugins/gem.py
smbl/prog/plugins/art.py
smbl/prog/plugins/last.py
smbl/prog/plugins/cmake.py
smbl/prog/plugins/gnuplot.py
smbl/prog/plugins/mrfast.py
smbl/prog/plugins/bcftools.py
smbl/prog/plugins/sambamba.py
smbl/prog/plugins/dwgsim.py
smbl/prog/plugins/bfast.py
smbl/prog/plugins/mrsfast.py
smbl/prog/plugins/wgsim.py
smbl/prog/plugins/storm.py
smbl/prog/plugins/pbsim.py
smbl/prog/plugins/freec.py
smbl/prog/plugins/htslib.py
smbl/prog/plugins/twobittofa.py
smbl/prog/plugins/__init__.py
smbl/prog/plugins/samtools.py
smbl/prog/plugins/xs.py
smbl/prog/plugins/_program.py
smbl/prog/plugins/bwa.py
smbl/prog/plugins/perm.py
smbl/prog/plugins/sirfast.py
smbl/prog/plugins/drfast.py
smbl/prog/plugins/curesim.py
smbl/prog/plugins/picard.py
smbl/prog/plugins/deprec/gmap_gsnap.py
smbl/messages/__init__.py
SMBL-0.1.1.post14.dist-info/DESCRIPTION.rst
SMBL-0.1.1.post14.dist-info/top_level.txt
SMBL-0.1.1.post14.dist-info/WHEEL
SMBL-0.1.1.post14.dist-info/pbr.json
SMBL-0.1.1.post14.dist-info/RECORD
SMBL-0.1.1.post14.dist-info/metadata.json
SMBL-0.1.1.post14.dist-info/METADATA
