Metadata-Version: 2.0
Name: SMBL
Version: 0.1.1.post14
Summary: SnakeMake Bioinformatics Library.
Home-page: http://github.com/karel-brinda/smbl
Author: Karel Břinda
Author-email: karel.brinda@gmail.com
License: MIT
Keywords: Bioinformatics,Computational Biology,Next-Generation Sequencing,Snakemake,Pipelines
Platform: UNKNOWN
Classifier: Development Status :: 4 - Beta
Classifier: Environment :: Console
Classifier: Intended Audience :: Science/Research
Classifier: License :: OSI Approved :: MIT License
Classifier: Natural Language :: English
Classifier: Programming Language :: Python :: 3
Classifier: Operating System :: Unix
Classifier: Topic :: Scientific/Engineering :: Bio-Informatics
Requires-Dist: pbr (>=0.10.8)
Requires-Dist: snakemake (>=3.2.1)
Requires-Dist: pytest
Requires-Dist: termcolor
